probcolli/__init__.py
probcolli/entities/__init__.py
probcolli/features/cbnn/__init__.py
probcolli/features/cbnn/cbnn.py
probcolli/features/cbnn/entities/__init__.py
probcolli/features/cbnn/entities/cbnn_info.py
probcolli/features/cgp/__init__.py
probcolli/features/cgp/cgp.py
probcolli/features/cgp/entities/__init__.py
probcolli/features/cgp/entities/cgp_info.py
probcolli/features/cgp/use_cases/__init__.py
probcolli/features/cgp/use_cases/gp_model.py
probcolli/features/cgp/use_cases/pg_likelihood.py
probcolli-0.1.5.dist-info/LICENSE
probcolli-0.1.5.dist-info/METADATA
probcolli-0.1.5.dist-info/WHEEL
probcolli-0.1.5.dist-info/top_level.txt
probcolli-0.1.5.dist-info/RECORD
